aryansindhi_101703110_missing_1/__init__.py
aryansindhi_101703110_missing_1/missing_data.py
aryansindhi_101703110_missing_1-0.0.1.dist-info/LICENSE
aryansindhi_101703110_missing_1-0.0.1.dist-info/METADATA
aryansindhi_101703110_missing_1-0.0.1.dist-info/WHEEL
aryansindhi_101703110_missing_1-0.0.1.dist-info/top_level.txt
aryansindhi_101703110_missing_1-0.0.1.dist-info/RECORD
