Metadata-Version: 2.1
Name: aryansindhi-101703110-missing-1
Version: 0.0.1
Summary: A small package that handles missing values in pandas dataframe
Home-page: UNKNOWN
Author: Aryan Sindhi
Author-email: asindhi_be17@thapar.edu
License: UNKNOWN
Platform: UNKNOWN
Classifier: Programming Language :: Python :: 3
Classifier: License :: OSI Approved :: MIT License
Classifier: Operating System :: OS Independent
Requires-Python: >=3.6
